jyafn-0.3.1.dist-info/METADATA
jyafn-0.3.1.dist-info/WHEEL
jyafn-0.3.1.dist-info/entry_points.txt
jyafn/cli/__init__.py
jyafn/cli/ext.py
jyafn/cli/cloud.py
jyafn/jyafn.pyi
jyafn/py.typed
jyafn/describe.py
jyafn/__init__.py
jyafn/np_dropin.py
jyafn/cloud.py
jyafn/jyafn.cpython-311-x86_64-linux-gnu.so
jyafn-0.3.1.dist-info/RECORD
