Metadata-Version: 2.3
Name: jyafn
Version: 0.3.1
Classifier: Programming Language :: Rust
Classifier: Programming Language :: Python :: Implementation :: CPython
Classifier: Programming Language :: Python :: Implementation :: PyPy
Requires-Dist: numpy >=1.13
Requires-Dist: click >=8.1
Requires-Dist: click-default-group >=1.2
Requires-Dist: semver >=3
Requires-Dist: pyyaml >=6
Requires-Dist: requests >=2
Requires-Dist: pygments >=2
Requires-Python: >=3.10
